{
  "$schema": "https://mintlify.com/schema.json",
  "name": "NCT Docs",
  "logo": {
    "dark": "https://rmitnct.club/media/logos/transparent.png",
    "light": "https://rmitnct.club/media/logos/transparent.png",
    "href": "https://rmitnct.club/"
  },
  "favicon": "logo/logo.png",
  "css": "custom-styles.css",
  "defaultTheme": "dark",
  "toggleTheme": true,
  "colors": {
    "primary": "#4896AC",
    "light": "#E3EDF9",
    "dark": "#171624",
    "anchors": {
      "from": "#4896AC",
      "to": "#FBB61B"
    }
  },
  "topbarLinks": [
    {
      "name": "Support",
      "url": "mailto:contact@rmitnct.club"
    }
  ],
  "topbarCtaButton": {
    "name": "Get Started",
    "url": "https://rmitnct.club/login"
  },
  "tabs": [],
  "anchors": [
    {
      "name": "GitHub Repository",
      "icon": "github",
      "url": "https://github.com/rmit-nct/hub"
    }
  ],
  "navigation": [
    {
      "group": "Get Started",
      "pages": [
        "introduction",
        "development",
        "monorepo-architecture",
        "git-conventions",
        "local-supabase-development",
        "ci-cd-pipelines",
        "documenting"
      ]
    },
    {
      "group": "Hub",
      "pages": [
        "platform/index",
        "platform/workspace-routing",
        {
          "group": "Features",
          "pages": [
            "platform/features/command-center-dashboard",
            "platform/features/meet-together",
            "platform/features/user-management"
          ]
        },
        {
          "group": "Architecture",
          "pages": [
            "platform/architecture/api-routes",
            "platform/architecture/authentication",
            "platform/architecture/authorization",
            "platform/architecture/data-fetching",
            "platform/architecture/routing",
            "platform/architecture/trpc"
          ]
        },
        {
          "group": "Personalization",
          "pages": [
            "platform/personalization/themes",
            "platform/personalization/language"
          ]
        },
        {
          "group": "Applications",
          "pages": [
            "platform/applications/neo-chess",
            "platform/applications/neo-crush"
          ]
        }
      ]
    },
    {
      "group": "Learn",
      "pages": ["learn/index", "learn/examples/index"]
    }
  ],
  "footerSocials": {
    "facebook": "https://www.facebook.com/rmit.nct",
    "instagram": "https://instagram.com/rmit.nct",
    "github": "https://github.com/rmit-nct",
    "linkedin": "https://www.linkedin.com/company/rmit-nct"
  },
  "feedback": {
    "thumbsRating": true,
    "suggestEdit": true
  }
}
